tensorflow_io_plugin_gs/core/python/ops/libtensorflow_io_plugin_gs.so
tensorflow_io_plugin_gs_nightly-0.18.0.dev20210513213318.data/purelib/tensorflow_io/__init__.py
tensorflow_io_plugin_gs_nightly-0.18.0.dev20210513213318.data/purelib/tensorflow_io/arrow/__init__.py
tensorflow_io_plugin_gs_nightly-0.18.0.dev20210513213318.data/purelib/tensorflow_io/arrow/python/__init__.py
tensorflow_io_plugin_gs_nightly-0.18.0.dev20210513213318.data/purelib/tensorflow_io/arrow/python/ops/__init__.py
tensorflow_io_plugin_gs_nightly-0.18.0.dev20210513213318.data/purelib/tensorflow_io/arrow/python/ops/arrow_dataset_ops.py
tensorflow_io_plugin_gs_nightly-0.18.0.dev20210513213318.data/purelib/tensorflow_io/bigquery/__init__.py
tensorflow_io_plugin_gs_nightly-0.18.0.dev20210513213318.data/purelib/tensorflow_io/bigquery/python/__init__.py
tensorflow_io_plugin_gs_nightly-0.18.0.dev20210513213318.data/purelib/tensorflow_io/bigquery/python/ops/__init__.py
tensorflow_io_plugin_gs_nightly-0.18.0.dev20210513213318.data/purelib/tensorflow_io/bigquery/python/ops/bigquery_api.py
tensorflow_io_plugin_gs_nightly-0.18.0.dev20210513213318.data/purelib/tensorflow_io/core/__init__.py
tensorflow_io_plugin_gs_nightly-0.18.0.dev20210513213318.data/purelib/tensorflow_io/core/grpc/__init__.py
tensorflow_io_plugin_gs_nightly-0.18.0.dev20210513213318.data/purelib/tensorflow_io/core/python/__init__.py
tensorflow_io_plugin_gs_nightly-0.18.0.dev20210513213318.data/purelib/tensorflow_io/core/python/api/__init__.py
tensorflow_io_plugin_gs_nightly-0.18.0.dev20210513213318.data/purelib/tensorflow_io/core/python/api/audio.py
tensorflow_io_plugin_gs_nightly-0.18.0.dev20210513213318.data/purelib/tensorflow_io/core/python/api/genome.py
tensorflow_io_plugin_gs_nightly-0.18.0.dev20210513213318.data/purelib/tensorflow_io/core/python/api/image.py
tensorflow_io_plugin_gs_nightly-0.18.0.dev20210513213318.data/purelib/tensorflow_io/core/python/api/version.py
tensorflow_io_plugin_gs_nightly-0.18.0.dev20210513213318.dist-info/LICENSE
tensorflow_io_plugin_gs_nightly-0.18.0.dev20210513213318.dist-info/METADATA
tensorflow_io_plugin_gs_nightly-0.18.0.dev20210513213318.dist-info/WHEEL
tensorflow_io_plugin_gs_nightly-0.18.0.dev20210513213318.dist-info/top_level.txt
tensorflow_io_plugin_gs_nightly-0.18.0.dev20210513213318.dist-info/RECORD
