Metadata-Version: 2.1
Name: tensorflow-io-plugin-gs-nightly
Version: 0.18.0.dev20210513213318
Summary: TensorFlow IO
Home-page: https://github.com/tensorflow/io
Author: Google Inc.
Author-email: opensource@google.com
License: UNKNOWN
Download-URL: https://github.com/tensorflow/io/tags
Project-URL: Source, https://github.com/tensorflow/io
Project-URL: Bug Reports, https://github.com/tensorflow/io/issues
Project-URL: Documentation, https://tensorflow.org/io
Keywords: tensorflow io machine learning
Platform: UNKNOWN
Classifier: Development Status :: 4 - Beta
Classifier: Intended Audience :: Developers
Classifier: Intended Audience :: Education
Classifier: Intended Audience :: Science/Research
Classifier: License :: OSI Approved :: Apache Software License
Classifier: Programming Language :: Python :: 3
Classifier: Programming Language :: Python :: 3.5
Classifier: Programming Language :: Python :: 3.6
Classifier: Programming Language :: Python :: 3.7
Classifier: Programming Language :: Python :: 3.8
Classifier: Programming Language :: Python :: 3 :: Only
Classifier: Topic :: Scientific/Engineering
Classifier: Topic :: Scientific/Engineering :: Mathematics
Classifier: Topic :: Scientific/Engineering :: Artificial Intelligence
Classifier: Topic :: Software Development
Classifier: Topic :: Software Development :: Libraries
Classifier: Topic :: Software Development :: Libraries :: Python Modules
Requires-Python: >=3.5, <3.10
